takopi_preview/__init__.py
takopi_preview/backend.py
takopi_preview-0.3.2.dist-info/WHEEL
takopi_preview-0.3.2.dist-info/entry_points.txt
takopi_preview-0.3.2.dist-info/METADATA
takopi_preview-0.3.2.dist-info/RECORD
