Metadata-Version: 2.3
Name: takopi-preview
Version: 0.3.2
Summary: Tailscale preview command plugin for Takopi
Keywords: takopi,tailscale,preview
Author: ZKP2P
License: MIT License
Classifier: License :: OSI Approved :: MIT License
Classifier: Programming Language :: Python :: 3
Classifier: Programming Language :: Python :: 3.14
Classifier: Programming Language :: Python :: 3 :: Only
Classifier: Operating System :: OS Independent
Requires-Dist: takopi>=0.20.0
Requires-Python: >=3.14
Project-URL: Homepage, https://takopi.dev
